wagtail_pdf_view/__init__.py
wagtail_pdf_view/hooks.py
wagtail_pdf_view/mixins.py
wagtail_pdf_view/urls.py
wagtail_pdf_view/utils.py
wagtail_pdf_view/views.py
wagtail_pdf_view/widgets.py
wagtail_pdf_view/static/pdf.js/LICENSE
wagtail_pdf_view/static/pdf.js/build/pdf.mjs
wagtail_pdf_view/static/pdf.js/build/pdf.mjs.map
wagtail_pdf_view/static/pdf.js/build/pdf.sandbox.mjs
wagtail_pdf_view/static/pdf.js/build/pdf.sandbox.mjs.map
wagtail_pdf_view/static/pdf.js/build/pdf.worker.mjs
wagtail_pdf_view/static/pdf.js/build/pdf.worker.mjs.map
wagtail_pdf_view/static/pdf.js/web/compressed.tracemonkey-pldi-09.pdf
wagtail_pdf_view/static/pdf.js/web/debugger.css
wagtail_pdf_view/static/pdf.js/web/debugger.mjs
wagtail_pdf_view/static/pdf.js/web/viewer.css
wagtail_pdf_view/static/pdf.js/web/viewer.html
wagtail_pdf_view/static/pdf.js/web/viewer.mjs
wagtail_pdf_view/static/pdf.js/web/viewer.mjs.map
wagtail_pdf_view/static/pdf.js/web/cmaps/78-EUC-H.bcmap
wagtail_pdf_view/static/pdf.js/web/cmaps/78-EUC-V.bcmap
wagtail_pdf_view/static/pdf.js/web/cmaps/78-H.bcmap
wagtail_pdf_view/static/pdf.js/web/cmaps/78-RKSJ-H.bcmap
wagtail_pdf_view/static/pdf.js/web/cmaps/78-RKSJ-V.bcmap
wagtail_pdf_view/static/pdf.js/web/cmaps/78-V.bcmap
wagtail_pdf_view/static/pdf.js/web/cmaps/78ms-RKSJ-H.bcmap
wagtail_pdf_view/static/pdf.js/web/cmaps/78ms-RKSJ-V.bcmap
wagtail_pdf_view/static/pdf.js/web/cmaps/83pv-RKSJ-H.bcmap
wagtail_pdf_view/static/pdf.js/web/cmaps/90ms-RKSJ-H.bcmap
wagtail_pdf_view/static/pdf.js/web/cmaps/90ms-RKSJ-V.bcmap
wagtail_pdf_view/static/pdf.js/web/cmaps/90msp-RKSJ-H.bcmap
wagtail_pdf_view/static/pdf.js/web/cmaps/90msp-RKSJ-V.bcmap
wagtail_pdf_view/static/pdf.js/web/cmaps/90pv-RKSJ-H.bcmap
wagtail_pdf_view/static/pdf.js/web/cmaps/90pv-RKSJ-V.bcmap
wagtail_pdf_view/static/pdf.js/web/cmaps/Add-H.bcmap
wagtail_pdf_view/static/pdf.js/web/cmaps/Add-RKSJ-H.bcmap
wagtail_pdf_view/static/pdf.js/web/cmaps/Add-RKSJ-V.bcmap
wagtail_pdf_view/static/pdf.js/web/cmaps/Add-V.bcmap
wagtail_pdf_view-2.0.0.dist-info/LICENSE
wagtail_pdf_view-2.0.0.dist-info/METADATA
wagtail_pdf_view-2.0.0.dist-info/WHEEL
wagtail_pdf_view-2.0.0.dist-info/top_level.txt
wagtail_pdf_view-2.0.0.dist-info/RECORD
